feature_selectors/RFE.py
feature_selectors/__init__.py
random_RFE-0.1.0.dist-info/METADATA
random_RFE-0.1.0.dist-info/WHEEL
random_RFE-0.1.0.dist-info/top_level.txt
random_RFE-0.1.0.dist-info/RECORD
