Metadata-Version: 2.1
Name: random-RFE
Version: 0.1.0
Summary: 随机递归特征消除。在使用递归特征消除的过程中，加入随机因子，根据概率随机删除特征，更大的重要性具有更小的概率被删除。
Home-page: UNKNOWN
Author: kakarotte22
Author-email: zhuyanfei22@icloud.com
License: MIT
Keywords: RFE,random,feature select
Platform: UNKNOWN
Requires-Dist: bleach (==3.1.1)
Requires-Dist: certifi (==2019.11.28)
Requires-Dist: chardet (==3.0.4)
Requires-Dist: docutils (==0.16)
Requires-Dist: idna (==2.9)
Requires-Dist: importlib-metadata (==1.5.0)
Requires-Dist: joblib (==0.14.1)
Requires-Dist: keyring (==21.2.0)
Requires-Dist: numpy (==1.18.1)
Requires-Dist: pandas (==1.0.2)
Requires-Dist: pkginfo (==1.5.0.1)
Requires-Dist: Pygments (==2.6.1)
Requires-Dist: python-dateutil (==2.8.1)
Requires-Dist: pytz (==2019.3)
Requires-Dist: pywin32-ctypes (==0.2.0)
Requires-Dist: readme-renderer (==25.0)
Requires-Dist: requests (==2.23.0)
Requires-Dist: requests-toolbelt (==0.9.1)
Requires-Dist: scikit-learn (==0.22.2.post1)
Requires-Dist: scipy (==1.4.1)
Requires-Dist: six (==1.14.0)
Requires-Dist: tqdm (==4.43.0)
Requires-Dist: twine (==3.1.1)
Requires-Dist: urllib3 (==1.25.8)
Requires-Dist: webencodings (==0.5.1)
Requires-Dist: wincertstore (==0.2)
Requires-Dist: zipp (==3.1.0)
